{
    "window": {
        "width": 800,
        "height": 500,
        "title" : "SUPER MARIO!"
    },
    "actors": [
        {
            "name": "Mario",
            "type": "BaseActor",
            "module": "engine.actors.baseactor",
            "x": 400,
            "y": 300,
            "components": [
                {
                    "name": "sprite",
                    "type": "StaticSpriteComponent",
                    "module": "engine.components.staticspritecomponent",
                    "fileName": "assets/mario.png"
                },
                {
                    "name": "mario",
                    "type": "FreeMovementComponent",
                    "module": "engine.components.freemovementcomponent",
                    "boundingRect": {
                        "x": 400,
                        "y": 300,
                        "width": 800,
                        "height": 468
                    }
                },
                {
                    "name": "Collider",
                    "type": "ColliderComponent",
                    "module": "engine.components.collidercomponent",
                    "boundingRect": {
                        "x": 400,
                        "y": 300,
                        "width": 64,
                        "height": 64
                    }
                }
            ]
        },
        {
            "name": "Orange",
            "type": "BaseActor",
            "module": "engine.actors.baseactor",
            "x": 300,
            "y": 300,
            "components": [
                {
                    "name": "sprite",
                    "type": "StaticSpriteComponent",
                    "module": "engine.components.staticspritecomponent",
                    "fileName": "assets/orange_ghost.png"
                },
                {
                    "name": "Collider",
                    "type": "ColliderComponent",
                    "module": "engine.components.collidercomponent",
                    "boundingRect": {
                        "x": 300,
                        "y": 300,
                        "width": 64,
                        "height": 64
                    }
                }
            ]
        }
    ]
}